odoo/addons/survey_answer_generation/README.rst
odoo/addons/survey_answer_generation/__init__.py
odoo/addons/survey_answer_generation/__manifest__.py
odoo/addons/survey_answer_generation/i18n/es.po
odoo/addons/survey_answer_generation/i18n/it.po
odoo/addons/survey_answer_generation/i18n/survey_answer_generation.pot
odoo/addons/survey_answer_generation/models/__init__.py
odoo/addons/survey_answer_generation/models/survey_question.py
odoo/addons/survey_answer_generation/models/survey_survey.py
odoo/addons/survey_answer_generation/models/survey_user_input.py
odoo/addons/survey_answer_generation/readme/CONFIGURE.md
odoo/addons/survey_answer_generation/readme/CONTRIBUTORS.md
odoo/addons/survey_answer_generation/readme/DESCRIPTION.md
odoo/addons/survey_answer_generation/readme/USAGE.md
odoo/addons/survey_answer_generation/static/description/icon.png
odoo/addons/survey_answer_generation/static/description/index.html
odoo/addons/survey_answer_generation/views/survey_question_views.xml
odoo/addons/survey_answer_generation/views/survey_survey_views.xml
odoo/addons/survey_answer_generation/views/survey_user_input_views.xml
odoo_addon_survey_answer_generation-17.0.1.0.0.4.dist-info/METADATA
odoo_addon_survey_answer_generation-17.0.1.0.0.4.dist-info/WHEEL
odoo_addon_survey_answer_generation-17.0.1.0.0.4.dist-info/top_level.txt
odoo_addon_survey_answer_generation-17.0.1.0.0.4.dist-info/RECORD
